{
    "name": "UsoRecursoFisico",
    "fields": [
        {
            "fieldName": "registroFechaInicio",
            "fieldType": "Instant"
        },
        {
            "fieldName": "tipoRegistro",
            "fieldType": "TipoIniciod",
            "fieldValues": "Inicio,Fin"
        }
    ],
    "relationships": [
        {
            "relationshipType": "many-to-one",
            "otherEntityName": "recursosFisicos",
            "otherEntityRelationshipName": "usoRecursoFisico",
            "relationshipName": "recurso",
            "otherEntityField": "recurso"
        },
        {
            "relationshipType": "many-to-one",
            "otherEntityName": "user",
            "otherEntityRelationshipName": "usoRecursoFisico",
            "relationshipName": "user",
            "otherEntityField": "id"
        }
    ],
    "changelogDate": "20191022215119",
    "entityTableName": "uso_recurso_fisico",
    "dto": "no",
    "pagination": "infinite-scroll",
    "service": "serviceClass",
    "jpaMetamodelFiltering": true,
    "fluentMethods": true,
    "readOnly": false,
    "clientRootFolder": "",
    "applications": "*"
}